{"id": "loading", "path": "d:\\xinze\\Documents\\GitHub\\Time_Series_Research\\Time_Series_Prediction_after_inflexion\\Data\\py2sqlserver\\loading.py", "mtime": 1528464625, "size": 1356, "hash": "253bf158fa1995299ab8fc2d41557f12", "data_mtime": 1528622883, "dependencies": ["builtins", "abc", "typing"], "suppressed": ["pyodbc", "pandas"], "child_modules": [], "options": {"check_untyped_defs": false, "disallow_any_generics": false, "platform": "win32", "show_none_errors": true, "disallow_untyped_defs": false, "follow_imports_for_stubs": false, "disallow_untyped_calls": false, "disallow_any_decorated": false, "ignore_missing_imports": true, "warn_unused_ignores": false, "no_implicit_optional": false, "always_true": [], "quick_and_dirty": false, "ignore_errors": false, "strict_optional_whitelist": null, "warn_no_return": true, "cache_fine_grained": false, "disallow_any_unimported": false, "always_false": [], "warn_return_any": false, "strict_optional": false, "disallow_any_expr": false, "strict_boolean": false, "disallow_subclassing_any": false, "follow_imports": "silent", "disallow_untyped_decorators": false, "disallow_any_explicit": false}, "dep_prios": [5, 30, 30, 10, 10], "dep_lines": [1, 1, 1, 1, 2], "interface_hash": "96f1981e158124876967ba67b6bdc608", "version_id": "0.590", "ignore_all": false}
